son/__init__.py
son/interface.py
son/last.py
son/serialize.py
son/stream.py
son-0.4.2.dist-info/LICENSE
son-0.4.2.dist-info/WHEEL
son-0.4.2.dist-info/METADATA
son-0.4.2.dist-info/RECORD
