Metadata-Version: 2.1
Name: son
Version: 0.4.2
Summary: Tools to read and write .son files
Home-page: https://flokno.github.io/son/
License: ISC
Keywords: file format,data
Author: Florian Knoop
Requires-Python: >=3.5
Classifier: License :: OSI Approved
Classifier: Programming Language :: Python :: 3
Classifier: Programming Language :: Python :: 3.5
Classifier: Programming Language :: Python :: 3.6
Classifier: Programming Language :: Python :: 3.7
Classifier: Programming Language :: Python :: 3.8
Classifier: Programming Language :: Python :: 3.9
Requires-Dist: lz (>=0.11.0,<0.12.0)
Project-URL: Repository, https://github.com/flokno/son
